aliyun/instrumentation/dashscope/__init__.py
aliyun/instrumentation/dashscope/_request_attributes_extractor.py
aliyun/instrumentation/dashscope/_response_attributes_extractor.py
aliyun/instrumentation/dashscope/_with_span.py
aliyun/instrumentation/dashscope/_wrapper.py
aliyun/instrumentation/dashscope/package.py
aliyun/instrumentation/dashscope/utils.py
aliyun/instrumentation/dashscope/version.py
aliyun_instrumentation_dashscope-1.0.0.dist-info/METADATA
aliyun_instrumentation_dashscope-1.0.0.dist-info/WHEEL
aliyun_instrumentation_dashscope-1.0.0.dist-info/RECORD
